smart_slugify/__init__.py
smart_slugify/slugify.py
smart_slugify-0.1.2.dist-info/licenses/LICENCE
smart_slugify-0.1.2.dist-info/METADATA
smart_slugify-0.1.2.dist-info/WHEEL
smart_slugify-0.1.2.dist-info/top_level.txt
smart_slugify-0.1.2.dist-info/RECORD
