Metadata-Version: 2.4
Name: smart-slugify
Version: 0.1.2
Summary: A lightweight Python library for converting text to URL-friendly slugs with full Unicode support and zero dependencies
Author-email: Haider Ali <malikhaider0567@gmail.com>
License: MIT
Project-URL: homepage, https://github.com/ali-hai-der/smart-slugify
Project-URL: repository, https://github.com/ali-hai-der/smart-slugify
Project-URL: documentation, https://github.com/ali-hai-der/smart-slugify
Keywords: slugify,url,slug,unicode,transliteration
Requires-Python: >=3.7
License-File: LICENCE
Dynamic: license-file
